LICENSE
README.md
setup.cfg
setup.py
RpiMotorLib/RpiMotorLib.py
RpiMotorLib/RpiMotorScriptLib.py
RpiMotorLib/__init__.py
RpiMotorLib/rpi_dc_lib.py
RpiMotorLib/rpi_pservo_lib.py
RpiMotorLib/rpiservolib.py
rpimotorlib.egg-info/PKG-INFO
rpimotorlib.egg-info/SOURCES.txt
rpimotorlib.egg-info/dependency_links.txt
rpimotorlib.egg-info/requires.txt
rpimotorlib.egg-info/top_level.txt